flipvision/__init__.py
flipvision/__main__.py
flipvision/check_BLE_device_UUID_characteristics.py
flipvision/cli.py
flipvision/main.py
flipvision/parser.py
flipvision/sensor.py
flipvision-0.0.1.dist-info/METADATA
flipvision-0.0.1.dist-info/WHEEL
flipvision-0.0.1.dist-info/entry_points.txt
flipvision-0.0.1.dist-info/top_level.txt
flipvision-0.0.1.dist-info/RECORD
