Metadata-Version: 2.1
Name: flipvision
Version: 0.0.1
Summary: Detect tricks done on skateboard
Requires-Python: >=3.9
Requires-Dist: bleak==0.22.3
Provides-Extra: lint
Requires-Dist: nox==2024.10.9; extra == "lint"
Requires-Dist: flake8==7.1.1; extra == "lint"
Requires-Dist: pre-commit==4.0.1; extra == "lint"
Requires-Dist: black==24.10.0; extra == "lint"
Requires-Dist: isort==5.13.2; extra == "lint"
Requires-Dist: codespell==2.3.0; extra == "lint"
